{
  "sections": {
    "main": {
      "type": "main-page",
      "settings": {
        "padding_top": 0,
        "padding_bottom": 0
      }
    },
    "1664356345c77ed977": {
      "type": "multicolumn",
      "blocks": {
        "2f216d0a-59c0-4fd8-82f7-3348c88ad9c6": {
          "type": "column",
          "settings": {
            "image": "shopify:\/\/shop_images\/307646572_597415205506350_6918335523788025303_n.jpg",
            "title": "",
            "text": "",
            "link_label": "",
            "link": "shopify:\/\/pages\/w3"
          }
        },
        "02fa33df-dd82-4723-96d6-0a4e7e7a1612": {
          "type": "column",
          "settings": {
            "image": "shopify:\/\/shop_images\/blackmerle_221_newsletter_2_4_final_5f73fcbf-15e5-4bb6-9254-03767992eab6.jpg",
            "title": "",
            "text": "",
            "link_label": "",
            "link": "shopify:\/\/pages\/world_2"
          }
        },
        "415e459a-19a7-4125-b5b5-f7ed226dcca9": {
          "type": "column",
          "settings": {
            "image": "shopify:\/\/shop_images\/blackmerle_221_newsletter_1_3x4_0ab3ddca-36a4-42cb-9286-fecd3d44358f.jpg",
            "title": "",
            "text": "",
            "link_label": "",
            "link": "shopify:\/\/pages\/w1"
          }
        }
      },
      "block_order": [
        "2f216d0a-59c0-4fd8-82f7-3348c88ad9c6",
        "02fa33df-dd82-4723-96d6-0a4e7e7a1612",
        "415e459a-19a7-4125-b5b5-f7ed226dcca9"
      ],
      "settings": {
        "title": "",
        "heading_size": "h2",
        "image_width": "full",
        "image_ratio": "adapt",
        "columns_desktop": 3,
        "column_alignment": "left",
        "background_style": "none",
        "button_label": "",
        "button_link": "",
        "color_scheme": "background-1",
        "columns_mobile": "2",
        "swipe_on_mobile": false,
        "padding_top": 32,
        "padding_bottom": 28
      }
    }
  },
  "order": [
    "main",
    "1664356345c77ed977"
  ]
}
